pymks_share
