Metadata-Version: 1.0
Name: pymks-share
Version: 0.1.4
Summary: Support Package for PyMKS to access datasets
Home-page: UNKNOWN
Author: David Brough
Author-email: david.brough.0416@gmail.com
License: UNKNOWN
Platform: UNKNOWN
